[
    {
        "title": "festival-partner",
        "logos": [
            {
                "name": "Google",
                "url": "https://www.google.com.ua/intl/en/about/",
                "logoUrl": "../images/logos/google.svg"
            }
        ]
    },
    {
        "title": "gold-partner",
        "logos": [
            {
                "name": "JotForm",
                "url": "https://www.jotform.com/",
                "logoUrl": "../images/logos/jotform.png"
            },
            {
                "name": "GDG[x]",
                "url": "https://github.com/gdg-x",
                "logoUrl": "../images/logos/gdg-x.svg"
            }
        ]
    },
    {
      "title": "silver-partner",
      "logos": [
        {
          "name": "BordoBT",
          "url": "https://www.bordobt.com",
          "logoUrl": "../images/logos/bordo.png"
        }
      ]
  },
  {
    "title": "bronze-partner",
    "logos": [
      {
        "name": "Unicrow",
        "url": "https://www.unicrow.com",
        "logoUrl": "../images/logos/unicrow.png"
      }
    ]
  }
]
